src/__init__.py
src/app.py
azure_subscription_switcher-0.3.2.dist-info/LICENSE
azure_subscription_switcher-0.3.2.dist-info/METADATA
azure_subscription_switcher-0.3.2.dist-info/WHEEL
azure_subscription_switcher-0.3.2.dist-info/entry_points.txt
azure_subscription_switcher-0.3.2.dist-info/RECORD
