Metadata-Version: 2.3
Name: azure-subscription-switcher
Version: 0.3.2
Summary: CLI Utility tool to switch between azure subscriptions
License: MIT
Author: Lahiru Senevirathne
Author-email: lahiru.senevirathne@icloud.com
Requires-Python: >=3.9
Classifier: License :: OSI Approved :: MIT License
Classifier: Programming Language :: Python :: 3
Classifier: Programming Language :: Python :: 3.9
Classifier: Programming Language :: Python :: 3.10
Classifier: Programming Language :: Python :: 3.11
Classifier: Programming Language :: Python :: 3.12
Classifier: Programming Language :: Python :: 3.13
Requires-Dist: click (>=8.1.3,<9.0.0)
